solar_registry/__init__.py
solar_registry/cli.py
solar_registry/py.typed
solar_registry/commands/__init__.py
solar_registry/commands/meta_merger.py
solar_registry/model/__init__.py
solar_registry/model/asset.py
solar_registry/model/legacy.py
solar_registry/model/test_tool.py
solar_registry/service/__init__.py
solar_registry/service/cos_sync.py
solar_registry/service/generator.py
solar_registry/service/pr_generator.py
solar_registry/service/testtool.py
solar_registry/service/validator.py
solar_registry/util/__init__.py
solar_registry/util/file.py
solar_registry-0.4.1.dist-info/METADATA
solar_registry-0.4.1.dist-info/WHEEL
solar_registry-0.4.1.dist-info/entry_points.txt
solar_registry-0.4.1.dist-info/licenses/LICENSE
solar_registry-0.4.1.dist-info/RECORD
