Metadata-Version: 2.4
Name: solar-registry
Version: 0.4.1
Summary: Generate and merge meta data for testsolar test tools
Project-URL: repository, https://github.com/OpenTestSolar/solar-registry
Author-email: asiazhang <asiazhang2002@gmail.com>
License: MIT
License-File: LICENSE
Classifier: Development Status :: 5 - Production/Stable
Classifier: Intended Audience :: Developers
Classifier: Programming Language :: Python
Classifier: Programming Language :: Python :: 3
Classifier: Programming Language :: Python :: 3.9
Classifier: Programming Language :: Python :: 3.10
Classifier: Programming Language :: Python :: 3.11
Classifier: Programming Language :: Python :: 3.12
Requires-Python: >=3.9
Requires-Dist: cos-python-sdk-v5>=1.9.30
Requires-Dist: httpx>=0.27.2
Requires-Dist: loguru>=0.7.2
Requires-Dist: opnieuw>=3.0.0
Requires-Dist: pydantic>=2.7.1
Requires-Dist: pyyaml>=6.0.1
Requires-Dist: typer>=0.12.3
